{
  "0": {
    "cen_loss": 2.302716353225708,
    "cen_accuracy": 0.1
  },
  "1": {
    "cen_loss": 2.302716353225708,
    "cen_accuracy": 0.1
  },
  "2": {
    "cen_loss": 2.5322491497039796,
    "cen_accuracy": 0.1
  },
  "3": {
    "cen_loss": 5.106609346008301,
    "cen_accuracy": 0.1
  },
  "4": {
    "cen_loss": 4.735240271377563,
    "cen_accuracy": 0.1
  },
  "5": {
    "cen_loss": 7.793971845245362,
    "cen_accuracy": 0.1
  },
  "6": {
    "cen_loss": 6.367286191558838,
    "cen_accuracy": 0.1
  },
  "7": {
    "cen_loss": 5.570908517456055,
    "cen_accuracy": 0.1
  },
  "8": {
    "cen_loss": 5.424192882537842,
    "cen_accuracy": 0.1375
  },
  "9": {
    "cen_loss": 6.018821713256836,
    "cen_accuracy": 0.1
  },
  "10": {
    "cen_loss": 5.65375404586792,
    "cen_accuracy": 0.1594
  },
  "11": {
    "cen_loss": 4.894927937698364,
    "cen_accuracy": 0.1039
  },
  "12": {
    "cen_loss": 4.214437525177002,
    "cen_accuracy": 0.1134
  },
  "13": {
    "cen_loss": 3.4217656713485716,
    "cen_accuracy": 0.1831
  },
  "14": {
    "cen_loss": 2.7981963682174684,
    "cen_accuracy": 0.2426
  },
  "15": {
    "cen_loss": 2.560686138153076,
    "cen_accuracy": 0.2623
  },
  "16": {
    "cen_loss": 1.82185462474823,
    "cen_accuracy": 0.3925
  },
  "17": {
    "cen_loss": 1.5396368394851685,
    "cen_accuracy": 0.4794
  },
  "18": {
    "cen_loss": 1.5192509937286376,
    "cen_accuracy": 0.4894
  },
  "19": {
    "cen_loss": 1.3359062111854554,
    "cen_accuracy": 0.5473
  },
  "20": {
    "cen_loss": 1.2718539821147918,
    "cen_accuracy": 0.5664
  },
  "21": {
    "cen_loss": 1.1980298615455627,
    "cen_accuracy": 0.5899
  },
  "22": {
    "cen_loss": 1.1971059526920318,
    "cen_accuracy": 0.596
  },
  "23": {
    "cen_loss": 1.1045618815898894,
    "cen_accuracy": 0.6323
  },
  "24": {
    "cen_loss": 1.1390015602588655,
    "cen_accuracy": 0.6257
  },
  "25": {
    "cen_loss": 1.0645742558002471,
    "cen_accuracy": 0.6397
  },
  "26": {
    "cen_loss": 1.1088530639648437,
    "cen_accuracy": 0.636
  },
  "27": {
    "cen_loss": 0.9356579179048539,
    "cen_accuracy": 0.6843
  },
  "28": {
    "cen_loss": 0.9768189340591431,
    "cen_accuracy": 0.6708
  },
  "29": {
    "cen_loss": 1.016361166024208,
    "cen_accuracy": 0.6606
  },
  "30": {
    "cen_loss": 0.9639629776239396,
    "cen_accuracy": 0.6811
  },
  "31": {
    "cen_loss": 0.9502662057876587,
    "cen_accuracy": 0.6834
  },
  "32": {
    "cen_loss": 0.9998672159433365,
    "cen_accuracy": 0.6731
  },
  "33": {
    "cen_loss": 0.9134836118459702,
    "cen_accuracy": 0.6909
  },
  "34": {
    "cen_loss": 0.9458751307725907,
    "cen_accuracy": 0.684
  },
  "35": {
    "cen_loss": 0.9153177413463592,
    "cen_accuracy": 0.6953
  },
  "36": {
    "cen_loss": 0.9137101108789444,
    "cen_accuracy": 0.6982
  },
  "37": {
    "cen_loss": 0.8585316315174103,
    "cen_accuracy": 0.7151
  },
  "38": {
    "cen_loss": 0.9225992464065552,
    "cen_accuracy": 0.699
  },
  "39": {
    "cen_loss": 0.9141667162179947,
    "cen_accuracy": 0.6977
  },
  "40": {
    "cen_loss": 0.8334044869184494,
    "cen_accuracy": 0.7247
  },
  "41": {
    "cen_loss": 0.8411775840520859,
    "cen_accuracy": 0.7184
  },
  "42": {
    "cen_loss": 0.8354767088890076,
    "cen_accuracy": 0.7213
  },
  "43": {
    "cen_loss": 0.8612902207612991,
    "cen_accuracy": 0.716
  },
  "44": {
    "cen_loss": 0.8473957275152206,
    "cen_accuracy": 0.7198
  },
  "45": {
    "cen_loss": 0.8734770419359207,
    "cen_accuracy": 0.7199
  },
  "46": {
    "cen_loss": 0.8318163128614425,
    "cen_accuracy": 0.7263
  },
  "47": {
    "cen_loss": 0.815578824043274,
    "cen_accuracy": 0.7368
  },
  "48": {
    "cen_loss": 0.8635165982723236,
    "cen_accuracy": 0.7203
  },
  "49": {
    "cen_loss": 0.8259262043714524,
    "cen_accuracy": 0.7312
  },
  "50": {
    "cen_loss": 0.8706021938562393,
    "cen_accuracy": 0.7204
  },
  "51": {
    "cen_loss": 0.8138032962322235,
    "cen_accuracy": 0.736
  },
  "52": {
    "cen_loss": 0.8364464303970337,
    "cen_accuracy": 0.7269
  },
  "53": {
    "cen_loss": 0.8675010392904282,
    "cen_accuracy": 0.7173
  },
  "54": {
    "cen_loss": 0.8472523565292358,
    "cen_accuracy": 0.7258
  },
  "55": {
    "cen_loss": 0.8840024034976959,
    "cen_accuracy": 0.7177
  },
  "56": {
    "cen_loss": 0.8052595521450042,
    "cen_accuracy": 0.7371
  },
  "57": {
    "cen_loss": 0.8194999606609344,
    "cen_accuracy": 0.7318
  },
  "58": {
    "cen_loss": 0.9029398918151855,
    "cen_accuracy": 0.7123
  },
  "59": {
    "cen_loss": 0.7782171091079712,
    "cen_accuracy": 0.7463
  },
  "60": {
    "cen_loss": 0.7587490793466568,
    "cen_accuracy": 0.7522
  },
  "61": {
    "cen_loss": 0.7890407185792923,
    "cen_accuracy": 0.7481
  },
  "62": {
    "cen_loss": 0.7845203071832657,
    "cen_accuracy": 0.746
  },
  "63": {
    "cen_loss": 0.801134726190567,
    "cen_accuracy": 0.7388
  },
  "64": {
    "cen_loss": 0.7915923777341842,
    "cen_accuracy": 0.7475
  },
  "65": {
    "cen_loss": 0.7720934578180313,
    "cen_accuracy": 0.7496
  },
  "66": {
    "cen_loss": 0.7913139919996262,
    "cen_accuracy": 0.7472
  },
  "67": {
    "cen_loss": 0.7546409557819367,
    "cen_accuracy": 0.759
  },
  "68": {
    "cen_loss": 0.8257735493898392,
    "cen_accuracy": 0.7323
  },
  "69": {
    "cen_loss": 0.8121100738525391,
    "cen_accuracy": 0.7416
  },
  "70": {
    "cen_loss": 0.7894933178186416,
    "cen_accuracy": 0.7495
  },
  "71": {
    "cen_loss": 0.8129616920232773,
    "cen_accuracy": 0.7431
  },
  "72": {
    "cen_loss": 0.8482308628082276,
    "cen_accuracy": 0.7388
  },
  "73": {
    "cen_loss": 0.8477035301804543,
    "cen_accuracy": 0.7383
  },
  "74": {
    "cen_loss": 0.8011827897429467,
    "cen_accuracy": 0.7487
  },
  "75": {
    "cen_loss": 0.7876711569666862,
    "cen_accuracy": 0.7542
  },
  "76": {
    "cen_loss": 0.7746748752117157,
    "cen_accuracy": 0.7543
  },
  "77": {
    "cen_loss": 0.750945432627201,
    "cen_accuracy": 0.7619
  },
  "78": {
    "cen_loss": 0.7874894539356232,
    "cen_accuracy": 0.751
  },
  "79": {
    "cen_loss": 0.790665174293518,
    "cen_accuracy": 0.7504
  },
  "80": {
    "cen_loss": 0.7691610765814781,
    "cen_accuracy": 0.7551
  },
  "81": {
    "cen_loss": 0.8083504765748978,
    "cen_accuracy": 0.7419
  },
  "82": {
    "cen_loss": 0.7407263648629189,
    "cen_accuracy": 0.7596
  },
  "83": {
    "cen_loss": 0.7821267842292786,
    "cen_accuracy": 0.7535
  },
  "84": {
    "cen_loss": 0.7770440281391143,
    "cen_accuracy": 0.7566
  },
  "85": {
    "cen_loss": 0.7768562691092491,
    "cen_accuracy": 0.7527
  },
  "86": {
    "cen_loss": 0.7653905311584472,
    "cen_accuracy": 0.7566
  },
  "87": {
    "cen_loss": 0.7623451177000999,
    "cen_accuracy": 0.7601
  },
  "88": {
    "cen_loss": 0.7542777131557464,
    "cen_accuracy": 0.7567
  },
  "89": {
    "cen_loss": 0.7646646679282189,
    "cen_accuracy": 0.7584
  },
  "90": {
    "cen_loss": 0.7961524626493454,
    "cen_accuracy": 0.7494
  },
  "91": {
    "cen_loss": 0.7637707064032555,
    "cen_accuracy": 0.7546
  },
  "92": {
    "cen_loss": 0.7514903612554074,
    "cen_accuracy": 0.7615
  },
  "93": {
    "cen_loss": 0.7722758255720139,
    "cen_accuracy": 0.756
  },
  "94": {
    "cen_loss": 0.7303233636379242,
    "cen_accuracy": 0.7637
  },
  "95": {
    "cen_loss": 0.7390659246921539,
    "cen_accuracy": 0.7642
  },
  "96": {
    "cen_loss": 0.7602384593605995,
    "cen_accuracy": 0.7571
  },
  "97": {
    "cen_loss": 0.7419162473917007,
    "cen_accuracy": 0.764
  },
  "98": {
    "cen_loss": 0.7327967660307885,
    "cen_accuracy": 0.769
  },
  "99": {
    "cen_loss": 0.7542550682306289,
    "cen_accuracy": 0.761
  },
  "100": {
    "cen_loss": 0.7539487736105919,
    "cen_accuracy": 0.7635
  },
  "101": {
    "cen_loss": 0.7201807588458061,
    "cen_accuracy": 0.7727
  }
}