{
  "0": {
    "cen_loss": 2.302704164505005,
    "cen_accuracy": 0.101375
  },
  "1": {
    "cen_loss": 2.302704164505005,
    "cen_accuracy": 0.101375
  },
  "2": {
    "cen_loss": 2.4546043777465822,
    "cen_accuracy": 0.101125
  },
  "3": {
    "cen_loss": 2.571876829147339,
    "cen_accuracy": 0.099375
  },
  "4": {
    "cen_loss": 2.445115955352783,
    "cen_accuracy": 0.098625
  },
  "5": {
    "cen_loss": 2.7184079341888427,
    "cen_accuracy": 0.101125
  },
  "6": {
    "cen_loss": 2.701570568084717,
    "cen_accuracy": 0.098625
  },
  "7": {
    "cen_loss": 2.514582227706909,
    "cen_accuracy": 0.102
  },
  "8": {
    "cen_loss": 2.5972890605926513,
    "cen_accuracy": 0.098875
  },
  "9": {
    "cen_loss": 2.7243026065826417,
    "cen_accuracy": 0.119125
  },
  "10": {
    "cen_loss": 2.944145477294922,
    "cen_accuracy": 0.248125
  },
  "11": {
    "cen_loss": 2.300303981781006,
    "cen_accuracy": 0.136375
  },
  "12": {
    "cen_loss": 2.4072960567474366,
    "cen_accuracy": 0.187
  },
  "13": {
    "cen_loss": 2.534744291305542,
    "cen_accuracy": 0.272125
  },
  "14": {
    "cen_loss": 2.4190105743408203,
    "cen_accuracy": 0.24275
  },
  "15": {
    "cen_loss": 2.158373601913452,
    "cen_accuracy": 0.311375
  },
  "16": {
    "cen_loss": 2.8919660606384276,
    "cen_accuracy": 0.29125
  },
  "17": {
    "cen_loss": 2.9427513122558593,
    "cen_accuracy": 0.337375
  },
  "18": {
    "cen_loss": 2.2903338623046876,
    "cen_accuracy": 0.274375
  },
  "19": {
    "cen_loss": 2.027309718132019,
    "cen_accuracy": 0.337375
  },
  "20": {
    "cen_loss": 2.232001792907715,
    "cen_accuracy": 0.365625
  },
  "21": {
    "cen_loss": 2.3488232316970827,
    "cen_accuracy": 0.275625
  },
  "22": {
    "cen_loss": 2.096424931526184,
    "cen_accuracy": 0.3165
  },
  "23": {
    "cen_loss": 1.776366828918457,
    "cen_accuracy": 0.388625
  },
  "24": {
    "cen_loss": 1.9640160655975343,
    "cen_accuracy": 0.34325
  },
  "25": {
    "cen_loss": 1.9541485471725464,
    "cen_accuracy": 0.338125
  },
  "26": {
    "cen_loss": 1.7916551561355591,
    "cen_accuracy": 0.367125
  },
  "27": {
    "cen_loss": 2.1016937808990477,
    "cen_accuracy": 0.330375
  },
  "28": {
    "cen_loss": 2.11117498588562,
    "cen_accuracy": 0.375
  },
  "29": {
    "cen_loss": 2.523507502555847,
    "cen_accuracy": 0.330875
  },
  "30": {
    "cen_loss": 2.61142639541626,
    "cen_accuracy": 0.37225
  },
  "31": {
    "cen_loss": 2.3991515159606935,
    "cen_accuracy": 0.33275
  },
  "32": {
    "cen_loss": 2.2031000833511354,
    "cen_accuracy": 0.315375
  },
  "33": {
    "cen_loss": 1.7409881868362427,
    "cen_accuracy": 0.40625
  },
  "34": {
    "cen_loss": 2.680381181716919,
    "cen_accuracy": 0.29025
  },
  "35": {
    "cen_loss": 2.0942139377593993,
    "cen_accuracy": 0.365875
  },
  "36": {
    "cen_loss": 1.7799998531341552,
    "cen_accuracy": 0.37575
  },
  "37": {
    "cen_loss": 2.2085418519973756,
    "cen_accuracy": 0.386
  },
  "38": {
    "cen_loss": 2.4327159280776978,
    "cen_accuracy": 0.283375
  },
  "39": {
    "cen_loss": 1.8909314432144164,
    "cen_accuracy": 0.361875
  },
  "40": {
    "cen_loss": 1.8723785390853882,
    "cen_accuracy": 0.398875
  },
  "41": {
    "cen_loss": 1.9089690914154054,
    "cen_accuracy": 0.378875
  },
  "42": {
    "cen_loss": 1.9780390357971191,
    "cen_accuracy": 0.383625
  },
  "43": {
    "cen_loss": 1.8072575969696045,
    "cen_accuracy": 0.4105
  },
  "44": {
    "cen_loss": 1.9632001857757568,
    "cen_accuracy": 0.37025
  },
  "45": {
    "cen_loss": 2.0006113138198853,
    "cen_accuracy": 0.414875
  },
  "46": {
    "cen_loss": 2.0502002782821656,
    "cen_accuracy": 0.348625
  },
  "47": {
    "cen_loss": 1.7928651580810546,
    "cen_accuracy": 0.436
  },
  "48": {
    "cen_loss": 2.0812160425186157,
    "cen_accuracy": 0.350625
  },
  "49": {
    "cen_loss": 2.686277280807495,
    "cen_accuracy": 0.300125
  },
  "50": {
    "cen_loss": 3.0901679096221923,
    "cen_accuracy": 0.306
  },
  "51": {
    "cen_loss": 1.59744903755188,
    "cen_accuracy": 0.450875
  },
  "52": {
    "cen_loss": 1.9632747087478637,
    "cen_accuracy": 0.362125
  },
  "53": {
    "cen_loss": 2.0013810567855836,
    "cen_accuracy": 0.40225
  },
  "54": {
    "cen_loss": 1.9914371767044068,
    "cen_accuracy": 0.395625
  },
  "55": {
    "cen_loss": 1.932155457496643,
    "cen_accuracy": 0.3715
  },
  "56": {
    "cen_loss": 1.6135309295654297,
    "cen_accuracy": 0.461125
  },
  "57": {
    "cen_loss": 1.8394111824035644,
    "cen_accuracy": 0.418625
  },
  "58": {
    "cen_loss": 1.7525785274505614,
    "cen_accuracy": 0.4295
  },
  "59": {
    "cen_loss": 2.398987766265869,
    "cen_accuracy": 0.33575
  },
  "60": {
    "cen_loss": 2.6576389389038084,
    "cen_accuracy": 0.32675
  },
  "61": {
    "cen_loss": 1.8794377555847168,
    "cen_accuracy": 0.430375
  },
  "62": {
    "cen_loss": 2.1047257461547852,
    "cen_accuracy": 0.37975
  },
  "63": {
    "cen_loss": 2.094879377365112,
    "cen_accuracy": 0.365625
  },
  "64": {
    "cen_loss": 2.1654022207260133,
    "cen_accuracy": 0.383125
  },
  "65": {
    "cen_loss": 2.0141352939605714,
    "cen_accuracy": 0.395125
  },
  "66": {
    "cen_loss": 1.6378823127746582,
    "cen_accuracy": 0.465125
  },
  "67": {
    "cen_loss": 1.6739895248413086,
    "cen_accuracy": 0.45725
  },
  "68": {
    "cen_loss": 1.8747270231246949,
    "cen_accuracy": 0.373875
  },
  "69": {
    "cen_loss": 1.81589821434021,
    "cen_accuracy": 0.380375
  },
  "70": {
    "cen_loss": 1.9485659914016724,
    "cen_accuracy": 0.3855
  },
  "71": {
    "cen_loss": 1.9179741935729981,
    "cen_accuracy": 0.39
  },
  "72": {
    "cen_loss": 1.7635000143051147,
    "cen_accuracy": 0.43575
  },
  "73": {
    "cen_loss": 1.8117774667739868,
    "cen_accuracy": 0.403375
  },
  "74": {
    "cen_loss": 1.7010196704864502,
    "cen_accuracy": 0.447125
  },
  "75": {
    "cen_loss": 1.9959231147766112,
    "cen_accuracy": 0.374875
  },
  "76": {
    "cen_loss": 1.8083763275146485,
    "cen_accuracy": 0.437875
  },
  "77": {
    "cen_loss": 1.803234305381775,
    "cen_accuracy": 0.395375
  },
  "78": {
    "cen_loss": 1.7519094285964967,
    "cen_accuracy": 0.481625
  },
  "79": {
    "cen_loss": 1.8398662443161011,
    "cen_accuracy": 0.42275
  },
  "80": {
    "cen_loss": 1.8385793924331666,
    "cen_accuracy": 0.42225
  },
  "81": {
    "cen_loss": 1.8402699632644652,
    "cen_accuracy": 0.432
  },
  "82": {
    "cen_loss": 1.6131989526748658,
    "cen_accuracy": 0.458875
  },
  "83": {
    "cen_loss": 1.9706986627578735,
    "cen_accuracy": 0.390125
  },
  "84": {
    "cen_loss": 1.6853513498306274,
    "cen_accuracy": 0.453
  },
  "85": {
    "cen_loss": 1.812892671585083,
    "cen_accuracy": 0.416875
  },
  "86": {
    "cen_loss": 1.5781231489181518,
    "cen_accuracy": 0.465
  },
  "87": {
    "cen_loss": 1.5112420439720153,
    "cen_accuracy": 0.488875
  },
  "88": {
    "cen_loss": 1.7706243915557862,
    "cen_accuracy": 0.430625
  },
  "89": {
    "cen_loss": 1.5378709020614625,
    "cen_accuracy": 0.4865
  },
  "90": {
    "cen_loss": 1.6018494901657105,
    "cen_accuracy": 0.498875
  },
  "91": {
    "cen_loss": 1.6018494901657105,
    "cen_accuracy": 0.498875
  },
  "92": {
    "cen_loss": 1.9029570398330689,
    "cen_accuracy": 0.3935
  },
  "93": {
    "cen_loss": 2.1434407463073732,
    "cen_accuracy": 0.399375
  },
  "94": {
    "cen_loss": 1.7941498222351073,
    "cen_accuracy": 0.423625
  },
  "95": {
    "cen_loss": 1.7168447704315186,
    "cen_accuracy": 0.45375
  },
  "96": {
    "cen_loss": 1.9938455228805543,
    "cen_accuracy": 0.378125
  },
  "97": {
    "cen_loss": 1.6728813943862915,
    "cen_accuracy": 0.447375
  },
  "98": {
    "cen_loss": 1.8536332759857177,
    "cen_accuracy": 0.391375
  },
  "99": {
    "cen_loss": 1.670870922088623,
    "cen_accuracy": 0.48625
  },
  "100": {
    "cen_loss": 1.6793364601135254,
    "cen_accuracy": 0.488875
  },
  "101": {
    "cen_loss": 1.6645617094039917,
    "cen_accuracy": 0.4725
  }
}